perfbench/__init__.py
perfbench/_bench_validators.py
perfbench/_core_validators.py
perfbench/bench.py
perfbench/core.py
perfbench/plotly_utils.py
perfbench/utils.py
perfbench/version.py
perfbench-4.0.1.dist-info/METADATA
perfbench-4.0.1.dist-info/RECORD
perfbench-4.0.1.dist-info/WHEEL
perfbench-4.0.1.dist-info/top_level.txt
