Metadata-Version: 2.1
Name: perfbench
Version: 4.0.1
Summary: perfbench measures execution time of code snippets with Timeit and uses Plotly to visualize the results.
Home-page: https://github.com/Hasenpfote/perfbench
Author: Hasenpfote
Author-email: Hasenpfote36@gmail.com
License: UNKNOWN
Keywords: benchmark,performance,plot,plotly
Platform: UNKNOWN
Classifier: Programming Language :: Python
Classifier: Programming Language :: Python :: 3
Classifier: Programming Language :: Python :: 3.4
Classifier: Programming Language :: Python :: 3.5
Classifier: Programming Language :: Python :: 3.6
Classifier: Programming Language :: Python :: 3.7
Classifier: License :: OSI Approved :: MIT License
Classifier: Operating System :: OS Independent
Classifier: Development Status :: 5 - Production/Stable
Classifier: Environment :: Other Environment
Classifier: Intended Audience :: Developers
Classifier: Topic :: Software Development
Classifier: Topic :: Utilities
Requires-Python: >=3.4
Requires-Dist: tqdm (>=4.6.1)
Requires-Dist: Cerberus (>=1.1)
Requires-Dist: plotly (>=3.0.0)
Requires-Dist: notebook (>=5.3)
Requires-Dist: ipywidgets (>=7.2)
